bitpost/__init__.py
bitpost/interface.py
bitpost/interface_for_bit.py
bitpost-1.1.5.dist-info/LICENSE
bitpost-1.1.5.dist-info/METADATA
bitpost-1.1.5.dist-info/WHEEL
bitpost-1.1.5.dist-info/top_level.txt
bitpost-1.1.5.dist-info/RECORD
