Metadata-Version: 2.1
Name: bitpost
Version: 1.1.5
Summary: Wrapper for the bitpost API
Home-page: https://github.com/bitpostAPI/interface-pypi.org
Author: Pedro FR
Author-email: pedro@bitpost.co
License: UNKNOWN
Platform: UNKNOWN
Classifier: Programming Language :: Python :: 3
Classifier: License :: OSI Approved :: MIT License
Classifier: Operating System :: OS Independent
Requires-Python: >=3.6
Requires-Dist: bit (>=0.7.2)
Requires-Dist: requests
